facebook_message_selenium_local/__init__.py
facebook_message_selenium_local/facebook_message_constants.py
facebook_message_selenium_local/facebook_message_selenium.py
facebook_message_selenium_local/facebook_selenium_util.py
facebook_message_selenium_local-0.0.26.dist-info/METADATA
facebook_message_selenium_local-0.0.26.dist-info/WHEEL
facebook_message_selenium_local-0.0.26.dist-info/top_level.txt
facebook_message_selenium_local-0.0.26.dist-info/RECORD
