Metadata-Version: 2.4
Name: facebook-message-selenium-local
Version: 0.0.26
Summary: PyPI Package for Circles facebook-message-selenium-local Python
Home-page: https://github.com/circles-zone/facebook-message-selenium-local-python-package
Author: Circles
Author-email: info@circlez.ai
Classifier: Programming Language :: Python :: 3
Classifier: License :: Other/Proprietary License
Classifier: Operating System :: OS Independent
Requires-Dist: logger-local
Requires-Dist: database-mysql-local
Requires-Dist: python-sdk-remote
Requires-Dist: message-local
Requires-Dist: selenium
Requires-Dist: chromedriver
Requires-Dist: chrome-boss
Requires-Dist: python-dotenv
Dynamic: author
Dynamic: author-email
Dynamic: classifier
Dynamic: description
Dynamic: description-content-type
Dynamic: home-page
Dynamic: requires-dist
Dynamic: summary
